full_adder/full_adder_example.v
module full_adder_dataflow (
    S,C,A,B,Cin
);
    
    input A,B,Cin;
    output S,C;

    assign S = A^B^Cin;
    assign C = (A&B)|(B&Cin)|(A&Cin);

endmodule

full_adder/full_adder_example_tb.v
`timescale 1ns/1ns
`include "full_adder_example.v"

module full_adder_example_tb;
  reg A,B,Cin;
  wire S,C;

  full_adder_dataflow uut (S,C,Cin,A,B);

  initial begin
    $display("Time \t A B Cin | S C");
    $monitor("%g \t %b %b %b | %b %b",$time,A,B,Cin,S,C);

    A=0;B=0;Cin=0; #10
    A=0;B=0;Cin=1; #10
    A=0;B=1;Cin=0; #10
    A=0;B=1;Cin=1; #10
    A=1;B=0;Cin=0; #10
    A=1;B=0;Cin=1; #10
    A=1;B=1;Cin=0; #10
    A=1;B=1;Cin=1; #10

    $finish;  
  end  


initial begin
    $dumpfile("full_adder_example.vcd");
    $dumpvars(0,full_adder_example_tb);
end

endmodule

full_adder/full_adder_example.vcd
$date
	Mon Dec 29 20:08:50 2025
$end
$version
	Icarus Verilog
$end
$timescale
	1ns
$end
$scope module full_adder_example_tb $end
$var wire 1 ! S $end
$var wire 1 " C $end
$var reg 1 # A $end
$var reg 1 $ B $end
$var reg 1 % Cin $end
$scope module uut $end
$var wire 1 % A $end
$var wire 1 # B $end
$var wire 1 " C $end
$var wire 1 $ Cin $end
$var wire 1 ! S $end
$upscope $end
$upscope $end
$enddefinitions $end
$comment Show the parameter values. $end
$dumpall
$end
#0
$dumpvars
0%
0$
0#
0"
0!
$end
#10
1!
1%
#20
1!
0%
1$
#30
0!
1"
1%
#40
0"
1!
0%
0$
1#
#50
1"
0!
1%
#60
0!
0%
1$
#70
1!
1%
